reg/__init__.py
reg/regi.py
regg-2.0.dist-info/LICENCE.txt
regg-2.0.dist-info/METADATA
regg-2.0.dist-info/WHEEL
regg-2.0.dist-info/top_level.txt
regg-2.0.dist-info/RECORD
